CryptoPaySDK/__init__.py
CryptoPaySDK/cryptopay.py
cryptopaysdk-1.5.1.dist-info/licenses/LICENSE
cryptopaysdk-1.5.1.dist-info/METADATA
cryptopaysdk-1.5.1.dist-info/WHEEL
cryptopaysdk-1.5.1.dist-info/top_level.txt
cryptopaysdk-1.5.1.dist-info/RECORD
